README.txt
setup.py
myanimelist/__init__.py
myanimelist/anime.py
myanimelist/anime_list.py
myanimelist/base.py
myanimelist/character.py
myanimelist/club.py
myanimelist/genre.py
myanimelist/manga.py
myanimelist/manga_list.py
myanimelist/media.py
myanimelist/media_list.py
myanimelist/myanimelist.py
myanimelist/person.py
myanimelist/producer.py
myanimelist/publication.py
myanimelist/session.py
myanimelist/tag.py
myanimelist/user.py
myanimelist/utilities.py
python_mal.egg-info/PKG-INFO
python_mal.egg-info/SOURCES.txt
python_mal.egg-info/dependency_links.txt
python_mal.egg-info/requires.txt
python_mal.egg-info/top_level.txt