Metadata-Version: 1.1
Name: python-mal
Version: 0.1.7
Summary: Provides programmatic access to MyAnimeList resources.
Home-page: https://github.com/shaldengeki/python-mal
Author: Shal Dengeki
Author-email: shaldengeki@gmail.com
License: LICENSE.txt
Download-URL: https://github.com/shaldengeki/python-mal/archive/master.zip
Platform: UNKNOWN
